Metadata-Version: 2.1
Name: tokeniser-py-lite
Version: 0.1.1
Summary: A custom tokeniser with a 131,072-token vocabulary derived from 0.5B (val) and 1B (val+test) tokens in SlimPajama. Lite version of the tokeniser-py library. Uses a novel token generation algorithm and a dynamic programming-based segmentation method for fast, interpretable tokenisation, which can also be used for tokeniation on custom token maps.
Home-page: https://github.com/Tasmay-Tibrewal/tokeniser-py-lite
Author: Tasmay Pankaj Tibrewal
Author-email: keshavtibrewal2@gmail.com
License: MIT
Keywords: Tokens,Tokeniser,Tokenizer,LLMs,LMs,LLM,LM,Language Model,Language Models,Large Language Models,Large Language Model
Classifier: Programming Language :: Python :: 3
License-File: LICENCE.txt
Requires-Dist: numpy
Requires-Dist: regex
Requires-Dist: tqdm
